.gitignore
LICENSE.txt
MANIFEST.in
__init__.py
setup.cfg
setup.py
OptiFit/___init___.py
OptiFit/models.py
OptiFit.egg-info/PKG-INFO
OptiFit.egg-info/SOURCES.txt
OptiFit.egg-info/dependency_links.txt
OptiFit.egg-info/requires.txt
OptiFit.egg-info/top_level.txt
OptiFit/examples/CompositeModel_fit_example.py
OptiFit/examples/RC_fit_example.py
OptiFit/__pycache__/models.cpython-39.pyc
OptiFit/examples/CompositeModel_fit_example.py
OptiFit/examples/RC_fit_conv_example.py
OptiFit/examples/RC_fit_example.py
OptiFit/examples/test_data.pkl
OptiFit/refractive_index_data/BP_eps.csv
OptiFit/refractive_index_data/crystalline_quartz(o)_1951-eV.csv
OptiFit/refractive_index_data/crystalline_quartz(o)_1999-eV.csv
OptiFit/refractive_index_data/graphite(o)_refractive_index_info-eV.csv
OptiFit/refractive_index_data/graphite(o)_refractive_index_info-nm.csv
OptiFit/refractive_index_data/hBN_refractive_index_info_2018-eV.csv
OptiFit/refractive_index_data/silica_refractive_index_info-eV.csv
OptiFit/refractive_index_data/silica_refractive_index_info-nm.csv
OptiFit/refractive_index_data/silicon_refractive_index_info-eV.csv
OptiFit/refractive_index_data/silicon_refractive_index_info-nm.csv